{
  "id": "business/gtm/product-market-fit/2026",
  "category": "business",
  "subcategory": "gtm",
  "topic": "product-market-fit",
  "version_tag": "2026",
  "canonical_question": "How do I measure product-market fit — signals, surveys, and thresholds?",
  "aliases": ["PMF measurement", "Sean Ellis test", "product-market fit survey", "40 percent test product-market fit"],
  "entity_type": "concept",
  "region": "global",
  "jurisdiction": "global",
  "confidence": 0.92,
  "token_estimate": 750,
  "source_count": 5,
  "md_path": "/business/gtm/product-market-fit/2026.md",
  "html_path": "/business/gtm/product-market-fit/2026.html",
  "priority": "high",
  "buy_links": []
}
