{
  "id": "software/patterns/oauth2-device-flow/2026",
  "category": "software",
  "subcategory": "patterns",
  "topic": "oauth2-device-flow",
  "version_tag": "2026",
  "canonical_question": "How do I implement OAuth2 Device Authorization flow?",
  "aliases": [
    "OAuth2 device flow",
    "device authorization grant",
    "RFC 8628 implementation",
    "device code flow",
    "OAuth for smart TV",
    "OAuth for CLI tools",
    "input-constrained device authentication",
    "OAuth2 device code grant"
  ],
  "entity_type": "software_reference",
  "region": "global",
  "jurisdiction": "global",
  "confidence": 0.90,
  "token_estimate": 3800,
  "source_count": 7,
  "md_path": "/software/patterns/oauth2-device-flow/2026.md",
  "html_path": "/software/patterns/oauth2-device-flow/2026.html",
  "priority": "medium",
  "buy_links": [],
  "temporal_validity": {
    "status": "stable",
    "last_breaking_change": "RFC 8628 published 2019-08; no breaking changes since — protocol is stable",
    "next_review": "2026-08-24",
    "change_sensitivity": "low"
  },
  "constraints": [
    "Polling interval MUST respect server-provided interval (default 5s) — slow_down adds 5s cumulatively",
    "device_code expires after expires_in seconds (typically 900-1800s) — must restart flow after expiry",
    "user_code MUST be displayed exactly as received — do not reformat or lowercase",
    "grant_type MUST be full URN: urn:ietf:params:oauth:grant-type:device_code",
    "Device flow clients are public clients — never embed client_secret in distributed apps"
  ]
}
