{
  "id": "finance/saas-metrics/magic-number-saas/2026",
  "category": "finance",
  "subcategory": "saas-metrics",
  "topic": "magic-number-saas",
  "version_tag": "2026",
  "canonical_question": "What is the SaaS Magic Number and what are good benchmarks?",
  "aliases": ["SaaS Magic Number formula", "Sales efficiency metric SaaS", "How to calculate SaaS Magic Number", "Magic Number benchmarks"],
  "entity_type": "concept",
  "region": "global",
  "jurisdiction": "global",
  "confidence": 0.90,
  "token_estimate": 750,
  "source_count": 4,
  "md_path": "/finance/saas-metrics/magic-number-saas/2026.md",
  "html_path": "/finance/saas-metrics/magic-number-saas/2026.html",
  "priority": "high",
  "buy_links": []
}
