{
  "id": "finance/startup-finance/saas-financial-model-spreadsheet-template/2026",
  "category": "finance",
  "subcategory": "startup-finance",
  "topic": "saas-financial-model-spreadsheet-template",
  "version_tag": "2026",
  "canonical_question": "How do I build a SaaS financial model — MRR waterfall, cohort analysis, P&L, cash flow, cap table, scenario toggles?",
  "aliases": [
    "SaaS financial model spreadsheet template",
    "How to build an MRR waterfall in Google Sheets",
    "SaaS startup financial projections template",
    "Three-statement SaaS model with cohort analysis",
    "SaaS cap table and scenario analysis spreadsheet"
  ],
  "entity_type": "execution_recipe",
  "region": "global",
  "jurisdiction": "global",
  "confidence": 0.88,
  "token_estimate": 3800,
  "source_count": 8,
  "md_path": "/finance/startup-finance/saas-financial-model-spreadsheet-template/2026.md",
  "html_path": "/finance/startup-finance/saas-financial-model-spreadsheet-template/2026.html",
  "priority": "medium",
  "buy_links": [],
  "temporal_validity": {
    "status": "evolving",
    "last_breaking_change": "SaaS valuation multiples compressed to 6-10x ARR median in 2025; CAC payback benchmarks shifted to 15 months median",
    "next_review": "2026-09-11",
    "change_sensitivity": "high"
  },
  "constraints": [
    "MRR waterfall must separate five components: New, Expansion, Contraction, Churn, Reactivation",
    "Cohort analysis requires minimum 6 months of data to produce meaningful retention curves",
    "Three-statement model must be integrated — P&L net income flows to cash flow, ending cash flows to balance sheet",
    "Scenario toggles must change only assumption cells, never formula cells",
    "Cap table must model SAFEs and convertible notes pre-conversion"
  ],
  "skip_this_unit_if": [
    {
      "condition": "User needs SaaS metrics definitions only, not a working model",
      "use_instead": "finance/saas-benchmarks/saas-metrics-glossary/2026"
    },
    {
      "condition": "User needs fundraising pitch deck financials, not a full operating model",
      "use_instead": "finance/startup-finance/fundraising-financial-summary/2026"
    },
    {
      "condition": "User is post-Series B and needs enterprise FP&A tooling",
      "use_instead": "software/financial-planning/enterprise-fpa-tool-comparison/2026"
    }
  ],
  "inputs_needed": [
    {
      "key": "tool_preference",
      "question": "Which spreadsheet tool should be used?",
      "type": "choice",
      "options": ["Google Sheets", "Microsoft Excel", "Causal/Mosaic (dedicated FP&A)", "no preference — auto-select"]
    },
    {
      "key": "technical_skill",
      "question": "What is the user's financial modeling skill level?",
      "type": "choice",
      "options": ["non-technical (needs guided templates)", "semi-technical (can edit formulas)", "developer/analyst (can build from scratch)"]
    },
    {
      "key": "stage",
      "question": "What stage is the SaaS company?",
      "type": "choice",
      "options": ["pre-revenue (projections only)", "early-revenue ($0-$50K MRR)", "growth ($50K-$500K MRR)", "scale ($500K+ MRR)"]
    },
    {
      "key": "fundraising_timeline",
      "question": "Is the user building this for fundraising?",
      "type": "choice",
      "options": ["yes, raising in 0-3 months", "yes, raising in 3-12 months", "no, internal planning only"]
    }
  ],
  "related_kos": {
    "depends_on": [
      {
        "id": "finance/startup-finance/startup-financial-projections-template/2026",
        "label": "General startup financial projections framework"
      }
    ],
    "related_to": [
      {
        "id": "finance/saas-benchmarks/saas-unit-economics-benchmarks/2026",
        "label": "Benchmark data to validate model assumptions"
      },
      {
        "id": "finance/saas-benchmarks/saas-arr-growth-benchmarks/2026",
        "label": "ARR growth rate benchmarks by stage"
      }
    ],
    "solves": [],
    "alternative_to": [],
    "often_confused_with": []
  }
}
