{
  "id": "finance/valuation/lbo-framework/2026",
  "category": "finance",
  "subcategory": "valuation",
  "topic": "lbo-framework",
  "version_tag": "2026",
  "canonical_question": "How does a leveraged buyout (LBO) model work?",
  "aliases": ["leveraged buyout model", "LBO analysis", "private equity buyout model", "LBO returns calculation"],
  "entity_type": "concept",
  "region": "global",
  "jurisdiction": "global",
  "confidence": 0.92,
  "token_estimate": 780,
  "source_count": 4,
  "md_path": "/finance/valuation/lbo-framework/2026.md",
  "html_path": "/finance/valuation/lbo-framework/2026.html",
  "priority": "medium",
  "buy_links": []
}
